geobr/__init__.py
geobr/constants.py
geobr/data/grid_state_correspondence_table.csv
geobr/list_geobr.py
geobr/lookup_muni.py
geobr/read_amazon.py
geobr/read_biomes.py
geobr/read_census_tract.py
geobr/read_comparable_areas.py
geobr/read_conservation_units.py
geobr/read_country.py
geobr/read_disaster_risk_area.py
geobr/read_health_facilities.py
geobr/read_health_region.py
geobr/read_immediate_region.py
geobr/read_indigenous_land.py
geobr/read_intermediate_region.py
geobr/read_meso_region.py
geobr/read_metro_area.py
geobr/read_micro_region.py
geobr/read_municipal_seat.py
geobr/read_municipality.py
geobr/read_neighborhood.py
geobr/read_pop_arrangements.py
geobr/read_region.py
geobr/read_schools.py
geobr/read_semiarid.py
geobr/read_state.py
geobr/read_urban_area.py
geobr/read_urban_concentrations.py
geobr/read_weighting_area.py
geobr/utils.py
geobr-0.1.10.dist-info/LICENSE.txt
geobr-0.1.10.dist-info/WHEEL
geobr-0.1.10.dist-info/METADATA
geobr-0.1.10.dist-info/RECORD
