Metadata-Version: 2.1
Name: geobr
Version: 0.1.10
Summary: geobr: Download Official Spatial Data Sets of Brazil
Home-page: https://github.com/ipeaGIT/geobr
License: MIT
Author: João Carabetta
Classifier: Intended Audience :: Developers
Classifier: Intended Audience :: Education
Classifier: Intended Audience :: Science/Research
Classifier: License :: OSI Approved :: MIT License
Classifier: Programming Language :: Python
Classifier: Programming Language :: Python :: 2
Classifier: Programming Language :: Python :: 2.7
Classifier: Programming Language :: Python :: 3
Classifier: Programming Language :: Python :: 3.10
Classifier: Programming Language :: Python :: 3.4
Classifier: Programming Language :: Python :: 3.5
Classifier: Programming Language :: Python :: 3.6
Classifier: Programming Language :: Python :: 3.7
Classifier: Programming Language :: Python :: 3.8
Classifier: Programming Language :: Python :: 3.9
Classifier: Topic :: Scientific/Engineering :: GIS
Classifier: Topic :: Scientific/Engineering :: Visualization
Requires-Dist: geopandas (>=0.7.0,<0.8.0)
Requires-Dist: shapely (>=1.7.0,<2.0.0)
Project-URL: Repository, https://github.com/ipeaGIT/geobr
